{
  "nabo, -en": {
    "dk": "nabo, -en",
    "se": "granne",
    "fi": "naapuri"
  },
  "nederdel, -en": {
    "dk": "nederdel, -en",
    "se": "kjol",
    "fi": "hame"
  },
  "nem": {
    "dk": "nem",
    "se": "lätt, enkel",
    "fi": "helppo"
  },
  "nemlig": {
    "dk": "nemlig",
    "se": "just, precis, nämligen",
    "fi": "juuri niin, nimittäin"
  },
  "netop": {
    "dk": "netop",
    "se": "just, precis",
    "fi": "juuri niin"
  },
  "næppe": {
    "dk": "næppe",
    "se": "knappast",
    "fi": "tuskin"
  },
  "nødig": {
    "dk": "nødig",
    "se": "ogärna",
    "fi": "vastahakoisesti"
  },
  "nødt til": {
    "dk": "nødt til",
    "se": "vara tvungen att",
    "fi": "pakko (tehdä jotain)"
  },
  "nøgle, -n": {
    "dk": "nøgle, -n",
    "se": "nyckel",
    "fi": "avain"
  },
  "nå": {
    "dk": "nå",
    "se": "hinna",
    "fi": "ehtiä"
  }
}